Workbook

Sheet Summary
A1: HCM360 HRIS — LGU Gap Analysis
A2: Municipality of Mariveles, Province of Bataan — Human Resource Management Office
A3: As Of April 22, 2026 · HCM360 v1.0.0
A5: Coverage Summary
A7: Status | B7: Count | C7: % of Total | D7: Meaning
A8: COVERED | B8: =COUNTIF('Full Matrix'!C:C,"COVERED") | C8: =B8/$B$11 | D8: Fully implemented — production-ready for LGU use
A9: PARTIAL | B9: =COUNTIF('Full Matrix'!C:C,"PARTIAL") | C9: =B9/$B$11 | D9: Exists; requires LGU-specific tuning, templates, or configuration
A10: GAP | B10: =COUNTIF('Full Matrix'!C:C,"GAP") | C10: =B10/$B$11 | D10: Needs new development before deployment
A11: TOTAL | B11: =SUM(B8:B10) | C11: 1 | D11: Requirements mapped from LGU document
A14: Critical Gaps — Top Priorities for LGU Deployment
A16: • CS Form No. 6 (revised 2020) — leave application strict compliance
A17: • CS Form No. 7 (s.2017) — Exit Interview
A18: • Personal Data Sheet (PDS) — CSC-prescribed template with versioning
A19: • IPCR / OPCR performance contract templates
A20: • Travel Order + Locator Slip modules (pre-approval + DTR integration)
A21: • Face-recognition + mobile geo-tagged check-in (flag raising/lowering)
A22: • Step Increment tracking (every 3 years from Date of Original Appointment)
A23: • Retirement monitoring (Age 60 early / 65 mandatory) + multi-recipient notice
A24: • Job Order / LSB / BHW / Nutritionist Scholar contract workflows
A25: • CSC Eligibility reporting split by 1st Level vs 2nd Level by gender

Sheet Full Matrix
A1: Section | B1: Requirement | C1: Status | D1: HCM360 Module | E1: Page / Route | F1: Gap / Notes | G1: Priority
A2: 1. CSC PRIME-HRM Level 2 | B2: Recruitment, Selection, Placement (RSP) | C2: COVERED | D2: Recruitment | E2: /recruitment | F2: Requisitions, candidates, CSC eligibilities, qualification standards | G2: Low
A3: 1. CSC PRIME-HRM Level 2 | B3: Performance Management (PM) | C3: COVERED | D3: Performance Management | E3: /performance | F3: Review cycles, KPIs, competency-based evaluation | G3: Low
A4: 1. CSC PRIME-HRM Level 2 | B4: Learning and Development (L&D) | C4: COVERED | D4: Learning & Development | E4: /learning | F4: Training catalog, enrollments, certifications | G4: Low
A5: 1. CSC PRIME-HRM Level 2 | B5: Rewards and Recognition (R&R) | C5: COVERED | D5: Rewards & Recognition | E5: /rewards | F5: Awards, praise wall, nominations | G5: Low
A6: 1. CSC PRIME-HRM Level 2 | B6: CSC PRIME-HRM Level 2 certification alignment | C6: PARTIAL | D6: All four modules | E6: /admin/reference | F6: Modules present; formal CSC audit alignment pending | G6: High
A7: 2. Report Generating (Functional) | B7: Data sources — pull from multiple DBs/systems | C7: COVERED | D7: Services | E7: services/db.py + reporting_service | F7: Centralized psycopg2 pool with view-based aggregation | G7: Low
A8: 2. Report Generating (Functional) | B8: Report design (drag-drop / designer) | C8: PARTIAL | D8: Analytics | E8: /reports (report builder) | F8: Saved queries + parameters; drag-drop UI would enhance | G8: Medium
A9: 2. Report Generating (Functional) | B9: Data analysis (query, analyze, summarize) | C9: COVERED | D9: Analytics | E9: /reports/demographics, /reports | F9: Materialized views + SQL-driven metrics | G9: Low
A10: 2. Report Generating (Functional) | B10: Manual + automated report generation | C10: COVERED | D10: Analytics + Reminders | E10: /admin/reminders, /reports | F10: Reminder rules can trigger scheduled reports | G10: Low
A11: 2. Report Generating (Functional) | B11: Output: screen, PDF, spreadsheet, print | C11: COVERED | D11: Reporting Service | E11: services/reporting_service.py | F11: PDF via ReportLab; CSV/Excel export available | G11: Low
A12: 2. Report Generating (Functional) | B12: Output: email distribution | C12: PARTIAL | D12: Reminders | E12: /admin/reminders | F12: Reminder engine exists; SMTP config must be wired in .env | G12: Medium
... A100: 14. Integration & Ecosystem | B100: Data import/export — migration, bulk updates | C100: COVERED | D100: Admin | E100: /admin/reference, /admin/demo-data | F100: CSV import tools + Demo Data profiles | G100: Low

Sheet Gap Backlog
A1: Gap Backlog — Items to Build for LGU Deployment
A3: ID | B3: Requirement | C3: Target Module | D3: Target Page / Route | E3: Effort Size | F3: Estimate | G3: Priority
A4: G01 | B4: CS Form No. 6 leave application template & strict workflow | C4: Leave Management | D4: /leave/requests/new (CS6 mode) | E4: Medium | F4: 2 weeks | G4: High
A5: G02 | B5: CS Form No. 7 Exit Interview template | C5: Offboarding + DMS | D5: /me/offboarding/cs7 | E5: Small | F5: 1 week | G5: High
A6: G03 | B6: Travel Order module with pre-approval + DTR integration | C6: New module | D6: /travel-orders | E6: Medium | F6: 3 weeks | G6: High
A7: G04 | B7: Locator Slip module with pre-approval | C7: New module | D7: /locator-slips | E7: Small | F7: 2 weeks | G7: High
A8: G05 | B8: Face-recognition attendance integration | C8: Attendance + 3rd-party | D8: mobile app + face-match API | E8: Large | F8: 6 weeks | G8: High
A9: G06 | B9: Mobile flag-raising/lowering check-in with photo + geotag | C9: Attendance + Mobile | D9: mobile app | E9: Large | F9: 6 weeks | G9: High
A10: G07 | B10: Job Order / LSB / BHW / Nutritionist Scholar contracts | C10: Recruitment | D10: /recruitment/contracts | E10: Medium | F10: 3 weeks | G10: High
A11: G08 | B11: Electronic signature on documents | C11: DMS | D11: /dms (e-sig integration) | E11: Medium | F11: 2 weeks | G11: High
A12: G09 | B12: Mobile training attendance with geotag + AM/PM | C12: L&D + Mobile | D12: mobile app | E12: Medium | F12: 3 weeks | G12: High
A13: G10 | B13: Training Narrative Report Form | C13: L&D | D13: /learning/narrative-report | E13: Small | F13: 1 week | G13: Medium
A14: G11 | B14: Loyalty Award auto-memo generator | C14: R&R + DMS | D14: /dms/certificate-types (Loyalty) | E14: Small | F14: 1 week | G14: Medium
... A21: G18 | B21: Attrition risk scoring model | C21: AI + Analytics | D21: /ai/insights | E21: Medium | F21: 3 weeks | G21: Medium
A22: Totals | B22: =COUNTA(A4:A21) & " items" | E22: Small: 6 / Medium: 10 / Large: 2 | G22: High: 15 / Med: 3

Sheet Partial Refinements
A1: Partial Refinements — Configuration & Minor Build Tasks
A3: ID | B3: Refinement | C3: Target Module | D3: Action
A4: P01 | B4: Seed CTO as leave type | C4: Leave | D4: Admin → Reference → lv_types → add CTO with OT accrual
A5: P02 | B5: IPCR / OPCR templates | C5: PM | D5: Add templates to performance review cycles
A6: P03 | B6: Job Portal posting integration | C6: RSP | D6: Add posting webhooks to 3rd-party job portals
A7: P04 | B7: Successor slate UI | C7: PM | D7: New tab on /performance showing critical roles + slate
A8: P05 | B8: CSC-specific employment types (JO, COS) | C8: Core HR | D8: Reference → employment_types → add JO, COS
A9: P06 | B9: Rank classification on positions | C9: Core HR | D9: Add rank_classification column to core.positions
A10: P07 | B10: Education bucket config per CSC | C10: Core HR | D10: Normalize education_level values; add report buckets
A11: P08 | B11: Plantilla Summary by gender | C11: Workforce Planning | D11: Extend existing scenario report with gender split
A12: P09 | B12: Next-in-rank auto notification on vacancy | C12: RSP + Reminders | D12: Add rank-based rule to reminder engine
A13: P10 | B13: Retention policy: 5 years for recruitment docs | C13: DMS | D13: Set retention_policies for Recruitment category
A14: P11 | B14: SMTP email delivery for reports/reminders | C14: Reminders | D14: Configure SMTP_HOST, SMTP_USER, SMTP_PASS in .env
... A23: P20 | B23: Retirement rules seeding (60 early, 65 mandatory) | C23: Core HR | D23: New reference table + age check on demographics

Sheet Module Coverage
A1: Coverage by HCM360 Module
A3: Module | B3: COVERED | C3: PARTIAL | D3: GAP | E3: Total | F3: Coverage %
A4: Core HR | B4: =COUNTIFS('Full Matrix'!D:D,"*"&A4&"*",'Full Matrix'!C:C,"COVERED") | C4: =COUNTIFS('Full Matrix'!D:D,"*"&A4&"*",'Full Matrix'!C:C,"PARTIAL") | D4: =COUNTIFS('Full Matrix'!D:D,"*"&A4&"*",'Full Matrix'!C:C,"GAP") | E4: =SUM(B4:D4) | F4: =IF(E4=0,0,B4/E4)
A5: Attendance | B5: =COUNTIFS('Full Matrix'!D:D,"*"&A5&"*",'Full Matrix'!C:C,"COVERED") | C5: =COUNTIFS('Full Matrix'!D:D,"*"&A5&"*",'Full Matrix'!C:C,"PARTIAL") | D5: =COUNTIFS('Full Matrix'!D:D,"*"&A5&"*",'Full Matrix'!C:C,"GAP") | E5: =SUM(B5:D5) | F5: =IF(E5=0,0,B5/E5)
A6: Leave Management | B6: =COUNTIFS('Full Matrix'!D:D,"*"&A6&"*",'Full Matrix'!C:C,"COVERED") | C6: =COUNTIFS('Full Matrix'!D:D,"*"&A6&"*",'Full Matrix'!C:C,"PARTIAL") | D6: =COUNTIFS('Full Matrix'!D:D,"*"&A6&"*",'Full Matrix'!C:C,"GAP") | E6: =SUM(B6:D6) | F6: =IF(E6=0,0,B6/E6)
A7: Payroll | B7: =COUNTIFS('Full Matrix'!D:D,"*"&A7&"*",'Full Matrix'!C:C,"COVERED") | C7: =COUNTIFS('Full Matrix'!D:D,"*"&A7&"*",'Full Matrix'!C:C,"PARTIAL") | D7: =COUNTIFS('Full Matrix'!D:D,"*"&A7&"*",'Full Matrix'!C:C,"GAP") | E7: =SUM(B7:D7) | F7: =IF(E7=0,0,B7/E7)
A8: Recruitment | B8: =COUNTIFS('Full Matrix'!D:D,"*"&A8&"*",'Full Matrix'!C:C,"COVERED") | C8: =COUNTIFS('Full Matrix'!D:D,"*"&A8&"*",'Full Matrix'!C:C,"PARTIAL") | D8: =COUNTIFS('Full Matrix'!D:D,"*"&A8&"*",'Full Matrix'!C:C,"GAP") | E8: =SUM(B8:D8) | F8: =IF(E8=0,0,B8/E8)
A9: Performance Management | B9: =COUNTIFS('Full Matrix'!D:D,"*"&A9&"*",'Full Matrix'!C:C,"COVERED") | C9: =COUNTIFS('Full Matrix'!D:D,"*"&A9&"*",'Full Matrix'!C:C,"PARTIAL") | D9: =COUNTIFS('Full Matrix'!D:D,"*"&A9&"*",'Full Matrix'!C:C,"GAP") | E9: =SUM(B9:D9) | F9: =IF(E9=0,0,B9/E9)
A10: Learning & Development | B10: =COUNTIFS('Full Matrix'!D:D,"*"&A10&"*",'Full Matrix'!C:C,"COVERED") | C10: =COUNTIFS('Full Matrix'!D:D,"*"&A10&"*",'Full Matrix'!C:C,"PARTIAL") | D10: =COUNTIFS('Full Matrix'!D:D,"*"&A10&"*",'Full Matrix'!C:C,"GAP") | E10: =SUM(B10:D10) | F10: =IF(E10=0,0,B10/E10)
A11: Rewards & Recognition | B11: =COUNTIFS('Full Matrix'!D:D,"*"&A11&"*",'Full Matrix'!C:C,"COVERED") | C11: =COUNTIFS('Full Matrix'!D:D,"*"&A11&"*",'Full Matrix'!C:C,"PARTIAL") | D11: =COUNTIFS('Full Matrix'!D:D,"*"&A11&"*",'Full Matrix'!C:C,"GAP") | E11: =SUM(B11:D11) | F11: =IF(E11=0,0,B11/E11)
A12: DMS | B12: =COUNTIFS('Full Matrix'!D:D,"*"&A12&"*",'Full Matrix'!C:C,"COVERED") | C12: =COUNTIFS('Full Matrix'!D:D,"*"&A12&"*",'Full Matrix'!C:C,"PARTIAL") | D12: =COUNTIFS('Full Matrix'!D:D,"*"&A12&"*",'Full Matrix'!C:C,"GAP") | E12: =SUM(B12:D12) | F12: =IF(E12=0,0,B12/E12)
A13: Workforce Planning | B13: =COUNTIFS('Full Matrix'!D:D,"*"&A13&"*",'Full Matrix'!C:C,"COVERED") | C13: =COUNTIFS('Full Matrix'!D:D,"*"&A13&"*",'Full Matrix'!C:C,"PARTIAL") | D13: =COUNTIFS('Full Matrix'!D:D,"*"&A13&"*",'Full Matrix'!C:C,"GAP") | E13: =SUM(B13:D13) | F13: =IF(E13=0,0,B13/E13)
A14: Analytics | B14: =COUNTIFS('Full Matrix'!D:D,"*"&A14&"*",'Full Matrix'!C:C,"COVERED") | C14: =COUNTIFS('Full Matrix'!D:D,"*"&A14&"*",'Full Matrix'!C:C,"PARTIAL") | D14: =COUNTIFS('Full Matrix'!D:D,"*"&A14&"*",'Full Matrix'!C:C,"GAP") | E14: =SUM(B14:D14) | F14: =IF(E14=0,0,B14/E14)
A15: ESS | B15: =COUNTIFS('Full Matrix'!D:D,"*"&A15&"*",'Full Matrix'!C:C,"COVERED") | C15: =COUNTIFS('Full Matrix'!D:D,"*"&A15&"*",'Full Matrix'!C:C,"PARTIAL") | D15: =COUNTIFS('Full Matrix'!D:D,"*"&A15&"*",'Full Matrix'!C:C,"GAP") | E15: =SUM(B15:D15) | F15: =IF(E15=0,0,B15/E15)
... A29: UI | B29: =COUNTIFS('Full Matrix'!D:D,"*"&A29&"*",'Full Matrix'!C:C,"COVERED") | C29: =COUNTIFS('Full Matrix'!D:D,"*"&A29&"*",'Full Matrix'!C:C,"PARTIAL") | D29: =COUNTIFS('Full Matrix'!D:D,"*"&A29&"*",'Full Matrix'!C:C,"GAP") | E29: =SUM(B29:D29) | F29: =IF(E29=0,0,B29/E29)
A30: ALL MODULES | B30: =SUM(B4:B29) | C30: =SUM(C4:C29) | D30: =SUM(D4:D29) | E30: =SUM(E4:E29) | F30: =IF(E30=0,0,B30/E30)

Sheet Roadmap
A1: Recommended Phasing for LGU Deployment
A3: Phase | B3: Timeline | C3: Theme | D3: Deliverable
A4: Phase 1 | B4: Weeks 1-4 | C4: LGU Readiness Baseline | D4: Configure reference data (CTO, JO, COS, rank classification, retention policies)
A5: Phase 1 | B5: Weeks 1-4 | C5: LGU Readiness Baseline | D5: Wire SMTP for reminders and report delivery
A6: Phase 1 | B6: Weeks 1-4 | C6: LGU Readiness Baseline | D6: Deploy behind TLS reverse proxy with production SECRET_KEY rotation
A7: Phase 1 | B7: Weeks 1-4 | C7: LGU Readiness Baseline | D7: Seed LGU-specific departments, positions, plantilla
A8: Phase 1 | B8: Weeks 1-4 | C8: LGU Readiness Baseline | D8: Train HR administrators on access matrix and privacy rules
A9: Phase 2 | B9: Weeks 5-10 | C9: Critical CSC Forms | D9: CS Form No. 6 leave application (strict)
A10: Phase 2 | B10: Weeks 5-10 | C10: Critical CSC Forms | D10: CS Form No. 7 exit interview
A11: Phase 2 | B11: Weeks 5-10 | C11: Critical CSC Forms | D11: Personal Data Sheet (PDS) with auto-fill
A12: Phase 2 | B12: Weeks 5-10 | C12: Critical CSC Forms | D12: IPCR / OPCR templates for performance reviews
A13: Phase 2 | B13: Weeks 5-10 | C13: Critical CSC Forms | D13: Travel Order + Locator Slip modules
A14: Phase 2 | B14: Weeks 5-10 | C14: Critical CSC Forms | D14: Loyalty Award, Step Increment, Retirement notice workflows
... A22: Phase 4 | B22: Weeks 17-20 | C22: Intelligence | D22: Drag-drop org-chart editor with vacancy overlay
