Workbook

Sheet Summary
A1: HCM360 HRIS — LGU Gap Analysis
A2: Municipality of Mariveles, Province of Bataan — Human Resource Management Office
A3: As Of April 24, 2026 · HCM360 v1.0.0
A5: Coverage Summary
A7: Status | B7: Count | C7: % of Total | D7: Meaning
A8: COVERED | B8: =COUNTIF('Full Matrix'!C:C,"COVERED") -> 89 | C8: =B8/$B$11 -> 0.78761062 | D8: Fully implemented — production-ready for LGU use
A9: PARTIAL | B9: =COUNTIF('Full Matrix'!C:C,"PARTIAL") -> 23 | C9: =B9/$B$11 -> 0.20353982 | D9: Exists; requires LGU-specific tuning, templates, or configuration
A10: GAP | B10: =COUNTIF('Full Matrix'!C:C,"GAP") -> 1 | C10: =B10/$B$11 -> 0.0088495575 | D10: Needs new development before deployment
A11: TOTAL | B11: =SUM(B8:B10) -> 113 | C11: 1 | D11: Requirements mapped from LGU document
A14: Critical Gaps — Top Priorities for LGU Deployment
A16: • CS Form No. 6 (revised 2020) — leave application strict compliance
A17: • CS Form No. 7 (s.2017) — Exit Interview
A18: • Personal Data Sheet (PDS) — CSC-prescribed template with versioning
A19: • IPCR / OPCR performance contract templates
A20: • Travel Order + Locator Slip modules (pre-approval + DTR integration)
A21: • Face-recognition + mobile geo-tagged check-in (flag raising/lowering)
A22: • Step Increment tracking (every 3 years from Date of Original Appointment)
A23: • Retirement monitoring (Age 60 early / 65 mandatory) + multi-recipient notice
A24: • Job Order / LSB / BHW / Nutritionist Scholar contract workflows
A25: • CSC Eligibility reporting split by 1st Level vs 2nd Level by gender

Sheet Full Matrix
A1: Section | B1: Requirement | C1: Status | D1: HCM360 Module | E1: Page / Route | F1: Gap / Notes | G1: Priority
A2: 1. CSC PRIME-HRM Level 2 | B2: Recruitment, Selection, Placement (RSP) | C2: COVERED | D2: Recruitment | E2: /recruitment | F2: Requisitions, candidates, CSC eligibilities, qualification standards | G2: Low
A3: 1. CSC PRIME-HRM Level 2 | B3: Performance Management (PM) | C3: COVERED | D3: Performance Management | E3: /performance | F3: Review cycles, KPIs, competency-based evaluation | G3: Low
A4: 1. CSC PRIME-HRM Level 2 | B4: Learning and Development (L&D) | C4: COVERED | D4: Learning & Development | E4: /learning | F4: Training catalog, enrollments, certifications | G4: Low
A5: 1. CSC PRIME-HRM Level 2 | B5: Rewards and Recognition (R&R) | C5: COVERED | D5: Rewards & Recognition | E5: /rewards | F5: Awards, praise wall, nominations | G5: Low
A6: 1. CSC PRIME-HRM Level 2 | B6: CSC PRIME-HRM Level 2 certification alignment | C6: PARTIAL | D6: All four modules | E6: /admin/reference | F6: Modules present; formal CSC audit alignment pending | G6: High
A7: 2. Report Generating (Functional) | B7: Data sources — pull from multiple DBs/systems | C7: COVERED | D7: Services | E7: services/db.py + reporting_service | F7: Centralized psycopg2 pool with view-based aggregation | G7: Low
A8: 2. Report Generating (Functional) | B8: Report design (drag-drop / designer) | C8: PARTIAL | D8: Analytics | E8: /reports (report builder) | F8: Saved queries + parameters; drag-drop UI would enhance | G8: Medium
A9: 2. Report Generating (Functional) | B9: Data analysis (query, analyze, summarize) | C9: COVERED | D9: Analytics | E9: /reports/demographics, /reports | F9: Materialized views + SQL-driven metrics | G9: Low
A10: 2. Report Generating (Functional) | B10: Manual + automated report generation | C10: COVERED | D10: Analytics + Reminders | E10: /admin/reminders, /reports | F10: Reminder rules can trigger scheduled reports | G10: Low
A11: 2. Report Generating (Functional) | B11: Output: screen, PDF, spreadsheet, print | C11: COVERED | D11: Reporting Service | E11: services/reporting_service.py | F11: PDF via ReportLab; CSV/Excel export available | G11: Low
A12: 2. Report Generating (Functional) | B12: Output: email distribution | C12: PARTIAL | D12: Reminders | E12: /admin/reminders | F12: Reminder engine exists; SMTP config must be wired in .env | G12: Medium
... A114: 14. Integration & Ecosystem | B114: Data import/export — migration, bulk updates | C114: COVERED | D114: Admin | E114: /admin/reference, /admin/demo-data | F114: CSV import tools + Demo Data profiles | G114: Low

Sheet Gap Backlog
A1: Gap Backlog — Items to Build for LGU Deployment
A3: ID | B3: Requirement | C3: Target Module | D3: Target Page / Route | E3: Effort Size | F3: Estimate | G3: Priority
A4: Totals | B4: =COUNTA(A3:A4) & " items" -> 2 items | E4: Small: 0 / Medium: 0 / Large: 0 | G4: High: 0 / Med: 0

Sheet Partial Refinements
A1: Partial Refinements — Configuration & Minor Build Tasks
A3: ID | B3: Refinement | C3: Target Module | D3: Action
A4: P01 | B4: Seed CTO as leave type | C4: Leave | D4: Admin → Reference → lv_types → add CTO with OT accrual
A5: P02 | B5: IPCR / OPCR templates | C5: PM | D5: Add templates to performance review cycles
A6: P03 | B6: Job Portal posting integration | C6: RSP | D6: Add posting webhooks to 3rd-party job portals
A7: P04 | B7: Successor slate UI | C7: PM | D7: New tab on /performance showing critical roles + slate
A8: P05 | B8: CSC-specific employment types (JO, COS) | C8: Core HR | D8: Reference → employment_types → add JO, COS
A9: P06 | B9: Rank classification on positions | C9: Core HR | D9: Add rank_classification column to core.positions
A10: P07 | B10: Education bucket config per CSC | C10: Core HR | D10: Normalize education_level values; add report buckets
A11: P08 | B11: Plantilla Summary by gender | C11: Workforce Planning | D11: Extend existing scenario report with gender split
A12: P09 | B12: Next-in-rank auto notification on vacancy | C12: RSP + Reminders | D12: Add rank-based rule to reminder engine
A13: P10 | B13: Retention policy: 5 years for recruitment docs | C13: DMS | D13: Set retention_policies for Recruitment category
A14: P11 | B14: SMTP email delivery for reports/reminders | C14: Reminders | D14: Configure SMTP_HOST, SMTP_USER, SMTP_PASS in .env
... A22: P20 | B22: Retirement rules seeding (60 early, 65 mandatory) | C22: Core HR | D22: New reference table + age check on demographics

Sheet Module Coverage
A1: Coverage by HCM360 Module
A3: Module | B3: COVERED | C3: PARTIAL | D3: GAP | E3: Total | F3: Coverage %
A4: Core HR | B4: =COUNTIFS('Full Matrix'!D:D,"*"&A4&"*",'Full Matrix'!C:C,"COVERED") -> 18 | C4: =COUNTIFS('Full Matrix'!D:D,"*"&A4&"*",'Full Matrix'!C:C,"PARTIAL") -> 4 | D4: =COUNTIFS('Full Matrix'!D:D,"*"&A4&"*",'Full Matrix'!C:C,"GAP") -> 0 | E4: =SUM(B4:D4) -> 22 | F4: =IF(E4=0,0,B4/E4) -> 0.81818182
A5: Attendance | B5: =COUNTIFS('Full Matrix'!D:D,"*"&A5&"*",'Full Matrix'!C:C,"COVERED") -> 6 | C5: =COUNTIFS('Full Matrix'!D:D,"*"&A5&"*",'Full Matrix'!C:C,"PARTIAL") -> 1 | D5: =COUNTIFS('Full Matrix'!D:D,"*"&A5&"*",'Full Matrix'!C:C,"GAP") -> 1 | E5: =SUM(B5:D5) -> 8 | F5: =IF(E5=0,0,B5/E5) -> 0.75
A6: Leave Management | B6: =COUNTIFS('Full Matrix'!D:D,"*"&A6&"*",'Full Matrix'!C:C,"COVERED") -> 2 | C6: =COUNTIFS('Full Matrix'!D:D,"*"&A6&"*",'Full Matrix'!C:C,"PARTIAL") -> 1 | D6: =COUNTIFS('Full Matrix'!D:D,"*"&A6&"*",'Full Matrix'!C:C,"GAP") -> 0 | E6: =SUM(B6:D6) -> 3 | F6: =IF(E6=0,0,B6/E6) -> 0.66666667
A7: Payroll | B7: =COUNTIFS('Full Matrix'!D:D,"*"&A7&"*",'Full Matrix'!C:C,"COVERED") -> 9 | C7: =COUNTIFS('Full Matrix'!D:D,"*"&A7&"*",'Full Matrix'!C:C,"PARTIAL") -> 0 | D7: =COUNTIFS('Full Matrix'!D:D,"*"&A7&"*",'Full Matrix'!C:C,"GAP") -> 0 | E7: =SUM(B7:D7) -> 9 | F7: =IF(E7=0,0,B7/E7) -> 1
A8: Recruitment | B8: =COUNTIFS('Full Matrix'!D:D,"*"&A8&"*",'Full Matrix'!C:C,"COVERED") -> 2 | C8: =COUNTIFS('Full Matrix'!D:D,"*"&A8&"*",'Full Matrix'!C:C,"PARTIAL") -> 2 | D8: =COUNTIFS('Full Matrix'!D:D,"*"&A8&"*",'Full Matrix'!C:C,"GAP") -> 0 | E8: =SUM(B8:D8) -> 4 | F8: =IF(E8=0,0,B8/E8) -> 0.5
A9: Performance Management | B9: =COUNTIFS('Full Matrix'!D:D,"*"&A9&"*",'Full Matrix'!C:C,"COVERED") -> 2 | C9: =COUNTIFS('Full Matrix'!D:D,"*"&A9&"*",'Full Matrix'!C:C,"PARTIAL") -> 1 | D9: =COUNTIFS('Full Matrix'!D:D,"*"&A9&"*",'Full Matrix'!C:C,"GAP") -> 0 | E9: =SUM(B9:D9) -> 3 | F9: =IF(E9=0,0,B9/E9) -> 0.66666667
A10: Learning & Development | B10: =COUNTIFS('Full Matrix'!D:D,"*"&A10&"*",'Full Matrix'!C:C,"COVERED") -> 1 | C10: =COUNTIFS('Full Matrix'!D:D,"*"&A10&"*",'Full Matrix'!C:C,"PARTIAL") -> 0 | D10: =COUNTIFS('Full Matrix'!D:D,"*"&A10&"*",'Full Matrix'!C:C,"GAP") -> 0 | E10: =SUM(B10:D10) -> 1 | F10: =IF(E10=0,0,B10/E10) -> 1
A11: Rewards & Recognition | B11: =COUNTIFS('Full Matrix'!D:D,"*"&A11&"*",'Full Matrix'!C:C,"COVERED") -> 1 | C11: =COUNTIFS('Full Matrix'!D:D,"*"&A11&"*",'Full Matrix'!C:C,"PARTIAL") -> 0 | D11: =COUNTIFS('Full Matrix'!D:D,"*"&A11&"*",'Full Matrix'!C:C,"GAP") -> 0 | E11: =SUM(B11:D11) -> 1 | F11: =IF(E11=0,0,B11/E11) -> 1
A12: DMS | B12: =COUNTIFS('Full Matrix'!D:D,"*"&A12&"*",'Full Matrix'!C:C,"COVERED") -> 2 | C12: =COUNTIFS('Full Matrix'!D:D,"*"&A12&"*",'Full Matrix'!C:C,"PARTIAL") -> 3 | D12: =COUNTIFS('Full Matrix'!D:D,"*"&A12&"*",'Full Matrix'!C:C,"GAP") -> 0 | E12: =SUM(B12:D12) -> 5 | F12: =IF(E12=0,0,B12/E12) -> 0.4
A13: Workforce Planning | B13: =COUNTIFS('Full Matrix'!D:D,"*"&A13&"*",'Full Matrix'!C:C,"COVERED") -> 0 | C13: =COUNTIFS('Full Matrix'!D:D,"*"&A13&"*",'Full Matrix'!C:C,"PARTIAL") -> 2 | D13: =COUNTIFS('Full Matrix'!D:D,"*"&A13&"*",'Full Matrix'!C:C,"GAP") -> 0 | E13: =SUM(B13:D13) -> 2 | F13: =IF(E13=0,0,B13/E13) -> 0
A14: Analytics | B14: =COUNTIFS('Full Matrix'!D:D,"*"&A14&"*",'Full Matrix'!C:C,"COVERED") -> 12 | C14: =COUNTIFS('Full Matrix'!D:D,"*"&A14&"*",'Full Matrix'!C:C,"PARTIAL") -> 2 | D14: =COUNTIFS('Full Matrix'!D:D,"*"&A14&"*",'Full Matrix'!C:C,"GAP") -> 0 | E14: =SUM(B14:D14) -> 14 | F14: =IF(E14=0,0,B14/E14) -> 0.85714286
A15: ESS | B15: =COUNTIFS('Full Matrix'!D:D,"*"&A15&"*",'Full Matrix'!C:C,"COVERED") -> 5 | C15: =COUNTIFS('Full Matrix'!D:D,"*"&A15&"*",'Full Matrix'!C:C,"PARTIAL") -> 0 | D15: =COUNTIFS('Full Matrix'!D:D,"*"&A15&"*",'Full Matrix'!C:C,"GAP") -> 0 | E15: =SUM(B15:D15) -> 5 | F15: =IF(E15=0,0,B15/E15) -> 1
... A32: Employee Picker | B32: =COUNTIFS('Full Matrix'!D:D,"*"&A32&"*",'Full Matrix'!C:C,"COVERED") -> 2 | C32: =COUNTIFS('Full Matrix'!D:D,"*"&A32&"*",'Full Matrix'!C:C,"PARTIAL") -> 0 | D32: =COUNTIFS('Full Matrix'!D:D,"*"&A32&"*",'Full Matrix'!C:C,"GAP") -> 0 | E32: =SUM(B32:D32) -> 2 | F32: =IF(E32=0,0,B32/E32) -> 1
A33: ALL MODULES | B33: =SUM(B4:B32) -> 92 | C33: =SUM(C4:C32) -> 24 | D33: =SUM(D4:D32) -> 1 | E33: =SUM(E4:E32) -> 117 | F33: =IF(E33=0,0,B33/E33) -> 0.78632479

Sheet Roadmap
A1: Recommended Phasing for LGU Deployment
A3: Phase | B3: Timeline | C3: Theme | D3: Deliverable
A4: Phase 1 | B4: Weeks 1-4 | C4: LGU Readiness Baseline | D4: Configure reference data (CTO, JO, COS, rank classification, retention policies)
A5: Phase 1 | B5: Weeks 1-4 | C5: LGU Readiness Baseline | D5: Wire SMTP for reminders and report delivery
A6: Phase 1 | B6: Weeks 1-4 | C6: LGU Readiness Baseline | D6: Deploy behind TLS reverse proxy with production SECRET_KEY rotation
A7: Phase 1 | B7: Weeks 1-4 | C7: LGU Readiness Baseline | D7: Seed LGU-specific departments, positions, plantilla
A8: Phase 1 | B8: Weeks 1-4 | C8: LGU Readiness Baseline | D8: Train HR administrators on access matrix and privacy rules
A9: Phase 2 | B9: Weeks 5-10 | C9: Critical CSC Forms | D9: CS Form No. 6 leave application (strict)
A10: Phase 2 | B10: Weeks 5-10 | C10: Critical CSC Forms | D10: CS Form No. 7 exit interview
A11: Phase 2 | B11: Weeks 5-10 | C11: Critical CSC Forms | D11: Personal Data Sheet (PDS) with auto-fill
A12: Phase 2 | B12: Weeks 5-10 | C12: Critical CSC Forms | D12: IPCR / OPCR templates for performance reviews
A13: Phase 2 | B13: Weeks 5-10 | C13: Critical CSC Forms | D13: Travel Order + Locator Slip modules
A14: Phase 2 | B14: Weeks 5-10 | C14: Critical CSC Forms | D14: Loyalty Award, Step Increment, Retirement notice workflows
... A22: Phase 4 | B22: Weeks 17-20 | C22: Intelligence | D22: Drag-drop org-chart editor with vacancy overlay

Sheet Features vs Requested
A1: Features Built vs Requested — Value-Add Scoring
A2: Inventory of every feature currently delivered, flagged against the Municipality of Mariveles HRMO requirements. "Bonus" rows were built beyond the original scope as added value.
A4: Scoring Summary
A6: Features Requested by LGU | B6: 100 | C6: 100%
A7: Requested — LIVE in current build | B7: 100 | C7: 100% of requested
A8: Bonus Features Beyond Request | B8: 77 | C8: +77% extra
A9: Total Features Delivered | B9: 177 | C9: 1.77x multiplier
A11: Feature Catalog
A13: Module | B13: Feature | C13: In LGU Request? | D13: Status | E13: Category
A14: Core HR | B14: Employee master (201 file) — 40+ fields | C14: YES | D14: LIVE | E14: Requested
A15: Core HR | B15: Sub-records: addresses, contacts, IDs, banks, dependents | C15: YES | D15: LIVE | E15: Requested
A16: Core HR | B16: Department hierarchy with head tracking | C16: YES | D16: LIVE | E16: Requested
A17: Core HR | B17: Position hierarchy + job grades | C17: YES | D17: LIVE | E17: Requested
A18: Core HR | B18: Employment type with probation + benefits flags | C18: YES | D18: LIVE | E18: Requested
A19: Core HR | B19: Employee status lifecycle (ACTIVE→REGULAR→RESIGNED…) | C19: YES | D19: LIVE | E19: Requested
A20: Core HR | B20: Transfer & promotion historical records | C20: YES | D20: LIVE | E20: Requested
A21: Core HR | B21: Bulk import / export (CSV) | C21: NO | D21: LIVE | E21: Bonus (Beyond Scope)
A22: Core HR | B22: Multi-tenant (per-company isolation) | C22: NO | D22: LIVE | E22: Bonus (Beyond Scope)
A23: Core HR | B23: Retirement Tracking (age 60 early / 65 mandatory) — G13 | C23: YES | D23: LIVE | E23: Requested
A24: Core HR | B24: Step Increment tracking (3-year cadence) — G12 | C24: YES | D24: LIVE | E24: Requested
... A190: Infrastructure | B190: Comprehensive tech + user documentation | C190: NO | D190: LIVE | E190: Bonus (Beyond Scope)

Sheet Job Requisition Gap
A1: Gap Analysis — Create Job Requisition Feature
A2: Focused deep-dive on the "Create Job Requisition" capability. Covers 8 categories: Data Model, Create Flow, Approval Workflow, Publication, Notifications, Access Control, Reporting, and Integration & Compliance. Each row shows whats in place today, whats missing, and the priority/effort estimate.
A4: Scoring Summary
A6: Total Aspects Analyzed | B6: 40 | C6: 100% of feature surface
A7: Already COVERED | B7: 40 | C7: 100%
A8: PARTIAL (needs refinement) | B8: 0 | C8: 0%
A9: GAP (must build) | B9: 0 | C9: 0%
A10: High-priority open items | B10: 0 | C10: build first
A11: Medium-priority open items | B11: 0 | C11: build next
A12: Low-priority open items | B12: 0 | C12: nice-to-have
A14: Feature Readiness
A15: Current feature readiness: 100% (COVERED counted as 1.0, PARTIAL as 0.5). To reach 100%, build the 0 GAP items below, starting with the 0 High-priority ones.
A17: Detailed Gap Analysis
A19: Category | B19: Aspect | C19: Current State | D19: Gap / Action Needed | E19: Status | F19: Priority | G19: Effort
A20: 1. Data Model | B20: Core requisition table exists | C20: recruitment.rec_requisitions with id, company_id, reference_no, department_id, position_id, headcount, justification, status, workflow_instance_id, requested_by, approved_by, target_hire_date, created_at | D20: None — fully in place | E20: COVERED | F20: Low | G20: Small
A21: 1. Data Model | B21: Audit trail on requisition changes | C21: Trigger audit_logs.fn_capture_change fires on INSERT/UPDATE/DELETE + rec_requisition_history table records every transition | D21: None — fully in place | E21: COVERED | F21: Low | G21: Small
A22: 1. Data Model | B22: Plantilla item linkage (LGU-specific) | C22: Migration 60: plantilla_item_id FK to rec_plantilla_items added | D22: None — plantilla dropdown in New Requisition form lets user pick any VACANT item | E22: COVERED | F22: High | G22: Small
A23: 1. Data Model | B23: Salary range on requisition | C23: Migration 60: salary_min_override + salary_max_override columns; PDF falls back to job_grade defaults when not set | D23: None — surfaced on both form and CSC Form PDF | E23: COVERED | F23: Medium | G23: Small
A24: 1. Data Model | B24: Budget / cost center link | C24: Migration 60: budget_source (TEXT) + funds_available (NUMERIC) columns; captured on form, rendered on CSC Form PDF | D24: None — Finance review fields live | E24: COVERED | F24: Medium | G24: Small
A25: 1. Data Model | B25: Supporting documents | C25: Migration 60: rec_requisition_attachments table + multipart upload endpoint POST /rsp/requisitions/<id>/attachments; type dropdown covers JUSTIFICATION / BUDGET_APPROVAL / ORG_CHART / ENDORSEMENT / OTHER | D25: None — attachments appear on detail page with size + uploader | E25: COVERED | F25: Medium | G25: Small
A26: 1. Data Model | B26: Requisition urgency / priority | C26: Migration 60: priority column (URGENT / HIGH / NORMAL / LOW) with CHECK constraint; colored chip on list + detail; URGENT auto-flags postings is_internal=TRUE | D26: None — priority drives inbox task priority + publish behaviour | E26: COVERED | F26: Low | G26: Small
A27: 1. Data Model | B27: CSC-specific fields (for government hiring) | C27: Migration 60: qualification_standard_id FK + required_eligibility_id FK; both dropdowns on the form; rendered under Section C of the CSC PDF | D27: None — civil service qualification metadata captured | E27: COVERED | F27: High | G27: Small
A28: 2. Create Flow | B28: Route: GET/POST /recruitment/requisitions/new | C28: Blueprint mounted at /rsp/requisitions with alias redirect from /recruitment/requisitions; GET renders form, POST calls create_requisition() | D28: None — form page live | E28: COVERED | F28: High | G28: Medium
A29: 2. Create Flow | B29: Service function: create_requisition() | C29: services/requisition_service.py:create_requisition(company_id, form, user_id, submit=False) returns (req_id, reference_no) | D29: None — service layer complete | E29: COVERED | F29: High | G29: Small
A30: 2. Create Flow | B30: Auto-generate reference_no (REQ-YYYY-NNNNNN) | C30: _next_reference_no() generates REQ-YYYY-NNNNNN (zero-padded sequence per year) via MAX(split_part(...)) lookup | D30: None — verified REQ-2026-000005 generated on test submission | E30: COVERED | F30: High | G30: Small
... A59: 8. Integration | B59: Integration with Workforce Planning scenarios | C59: wfp_warning() compares current + requested headcount against active WFP scenario planned_hc; amber banner on detail page when exceeded, naming the scenario and over_by delta | D59: None — WFP banner shows on detail page when over-plan | E59: COVERED | F59: Low | G59: Medium

Sheet Task Management Gap
A1: Gap Analysis — Task Management Feature
A2: Focused deep-dive on the Task Management capability. Today the platform has a PASSIVE inbox (system-generated tasks from workflow approvals and the reminder engine); it lacks user-initiated creation, assignment to others, collaboration, recurrence, and reporting. This sheet audits 9 categories: Data Model, Create Flow, Views, Collaboration, Recurrence, Notifications, Access Control, Reporting, and Integrations.
A4: Scoring Summary
A6: Total Aspects Analyzed | B6: 56 | C6: 100% of feature surface
A7: Already COVERED | B7: 26 | C7: 46%
A8: PARTIAL (needs refinement) | B8: 3 | C8: 5%
A9: GAP (must build) | B9: 27 | C9: 48%
A10: High-priority open items | B10: 0 | C10: build first
A11: Medium-priority open items | B11: 16 | C11: build next
A12: Low-priority open items | B12: 14 | C12: nice-to-have
A14: Feature Readiness
A15: Current feature readiness: 49% (COVERED counted as 1.0, PARTIAL as 0.5). Infrastructure (table, inbox page, workflow integration) is in place, but user-initiated creation, assignment, collaboration, recurrence, and reporting are not yet built. To reach 100%, build the 27 GAP items below, starting with the 0 High-priority ones.
A17: Detailed Gap Analysis
A19: Category | B19: Aspect | C19: Current State | D19: Gap / Action Needed | E19: Status | F19: Priority | G19: Effort
A20: 1. Data Model | B20: Core task table | C20: core.task_inbox with id, employee_id, user_id, task_type, title, description, action_url, priority, due_date, status, is_read, source_table, source_id, created_at, completed_at | D20: None — table exists and is used by workflow/reminder engines | E20: COVERED | F20: Low | G20: Small
A21: 1. Data Model | C21: employee_id column already captures the assignee | D21: None — populated by create_task() helper | E21: COVERED | F21: Low | G21: Small
A22: 1. Data Model | B22: Assigner (who CREATED the task) | C22: Migration 61: core.task_inbox.created_by BIGINT FK → core.users(id) added and backfilled; task_service.create_task() always sets it to the current user | D22: None — assigner is now audited on every task | E22: COVERED | F22: High | G22: Small
A23: 1. Data Model | B23: Task categories / tags | C23: task_type is a free-text string (REQUISITION_APPROVAL, LEAVE_APPROVAL, etc.) — not end-user selectable | D23: Add task_category enum (WORK, FOLLOWUP, MEETING, DOC_REVIEW, PERSONAL, SYSTEM) + tags VARCHAR(255) for free-tag; used for list filters and reporting | E23: PARTIAL | F23: Medium | G23: Small
A24: 1. Data Model | B24: Subtasks / checklist items | C24: None — task_inbox is flat | D24: New table core.task_subitems (id, task_id FK, title, is_completed, sort_order, completed_at) with cascade delete | E24: GAP | F24: Medium | G24: Small
A25: 1. Data Model | B25: Comments / discussion | C25: None — no comment table | D25: New table core.task_comments (id, task_id FK, user_id FK, body TEXT, created_at, edited_at) for collaboration thread | E25: GAP | F25: Medium | G25: Small
A26: 1. Data Model | B26: Attachments | C26: None — no attachment linkage | D26: New table core.task_attachments (id, task_id FK, file_name, file_path, mime_type, size_kb, uploaded_by, uploaded_at); reuse /uploads/tasks/<id>/ convention | E26: GAP | F26: Medium | G26: Small
A27: 1. Data Model | B27: Audit trail / history | C27: Status transitions timestamped via completed_at; no full audit log | D27: New table core.task_history (id, task_id, action, old_value, new_value, user_id, created_at); trigger on UPDATE to log status/priority/due_date/assignee changes | E27: GAP | F27: Medium | G27: Small
A28: 1. Data Model | B28: Recurring tasks metadata | C28: None — every task is one-shot | D28: Add recurrence_rule JSONB (RFC 5545 RRULE subset: DAILY/WEEKLY/MONTHLY + interval + count/until) + parent_recurrence_id; scheduler spawns the next occurrence on completion | E28: GAP | F28: Medium | G28: Medium
A29: 1. Data Model | B29: Estimated vs actual effort | C29: None — no time tracking fields | D29: Add estimated_minutes INT + actual_minutes INT; used for capacity planning reports | E29: GAP | F29: Low | G29: Small
A30: 1. Data Model | B30: Task dependencies / blocking | C30: None | D30: New table core.task_dependencies (task_id, depends_on_task_id, dep_type) — BLOCKS / BLOCKED_BY / RELATES_TO; surfaces as "Waiting on" chip | E30: GAP | F30: Low | G30: Medium
A31: 2. Create Flow | B31: System-generated task insertion | C31: task_inbox_service.create_task() called from workflow engine, reminder engine, requisition service — covers REQUISITION_APPROVAL, LEAVE_APPROVAL, REMINDER, etc. | D31: None — system-generated tasks land in inbox correctly | E31: COVERED | F31: Low | G31: Small
A32: 2. Create Flow | B32: User-initiated task creation (self-task) | C32: GET/POST /tasks/new live — renders form with title, description, priority, category, due date, and assignee autocomplete; modules/tasks/routes.py calls task_service.create_task() | D32: None — personal to-dos and self-tasks fully supported | E32: COVERED | F32: High | G32: Small
A33: 2. Create Flow | B33: Assign task to another user | C33: /tasks/new includes an AJAX assignee picker (GET /api/employees/search); non-admin roles are scoped to same-department teammates; assignment fires the TASK_ASSIGNED notification | D33: None — assignment flow live with autocomplete + dept scoping | E33: COVERED | F33: High | G33: Medium
... A75: 9. Integrations | B75: Mobile PWA support | C75: Inbox works on mobile browser but not installable as app | D75: Add web app manifest + service worker (offline-first for /me/inbox); install-to-home-screen prompt | E75: GAP | F75: Low | G75: Medium
